Workbook

Sheet Yearly
B1: Home Price: | C1: =Monthly!D1 -> 850000 | D1: Down Payment: | E1: =Monthly!F1 -> 0.2 | F1: Monthly Cost: | G1: =((SUM(E4:F4)/12)) -> 6172.515
A2: Year | B2: % Equity in Home | C2: Principal | D2: Interest | E2: Total Yearly Payment | F2: Taxes, HOA Fees, Insurance, Etc | G2: Tax Savings | H2: Interest Rate | I2: Sold Price | J2: Sold: Money Walk Away with | K2: Sold: Profit | L2: Cumulative Return % | M2: Sold: Profit if Renting after 5 years | N2: Cumulative Return % | P2: Year | Q2: Yearly Cost of Home Minus Rent | R2: Cumulative Profit | S2: Return Based on Principal | T2: Monthly Rent | U2: Yearly Rent
A3: 1 | B3: =SUM(C$3:C3)/C$1 -> 0.20928649 | C3: =SUMIF(Monthly!A$3:A$362, Yearly!A3, Monthly!D$3:D$362) -> 177893.52 | D3: =SUMIF(Monthly!A$3:A$362, Yearly!A3, Monthly!E$3:E$362) -> 42614.66 | E3: =SUM(C3:D3) -> 220508.18 | F3: =(9800+11262+2500) -> 23562 | H3: =Monthly!I3 -> 0.063 | I3: 1020141.4 | J3: =I3-SUM(D$3:D3)-SUM(F$3:F3)-SUM(C4:C$32)+G3 -> 281858.26 | K3: =I3-SUM(D$3:D3)-SUM(F$3:F3)-SUM(C$3:C$32)+SUM(G$3:G3) -> 103964.74 | L3: =K3/(SUM(C$3:D3)+SUM(F$3:F3)-SUM(G$3:G3)) -> 0.42596247 | M3: =I3-SUM(D$3:D3)-SUM(F$3:F3)-SUM(C$3:C$32)+SUM(G$3:G3) -> 103964.74 | N3: =M3/(SUM(C$3:D3)+SUM(F$3:F3)-SUM(G$3:G3)) -> 0.42596247 | P3: 1 | Q3: =-1*(SUM(D3)+F3-G3-U3) -> -24176.66 | R3: =Q3 -> -24176.66 | S3: =SUM(R3)/SUM(C$3:C3) -> -0.13590523 | T3: 3500 | U3: =T3*12 -> 42000
A4: =A3+1 -> 2 | B4: =SUM(C$3:C4)/C$1 -> 0.21917523 | C4: =SUMIF(Monthly!A$3:A$362, Yearly!A4, Monthly!D$3:D$362) -> 8405.4246 | D4: =SUMIF(Monthly!A$3:A$362, Yearly!A4, Monthly!E$3:E$362) -> 42102.755 | E4: =SUM(C4:D4) -> 50508.18 | F4: =(9800+11262+2500) -> 23562 | H4: =H3 -> 0.063 | I4: =(I3*0.05)+I3 -> 1071148.5 | J4: =I4-SUM(D$3:D4)-SUM(F$3:F4)-SUM(C5:C$32)+G4 -> 275606 | K4: =I4-SUM(D$3:D4)-SUM(F$3:F4)-SUM(C$3:C$32)+SUM(G$3:G4) -> 89307.052 | L4: =K4/(SUM(C$3:D4)+SUM(F$3:F4)-SUM(G$3:G4)) -> 0.28071588 | M4: =I4-SUM(D$3:D4)-SUM(F$3:F4)-SUM(C$3:C$32)+SUM(G$3:G4) -> 89307.052 | N4: =M4/(SUM(C$3:D4)+SUM(F$3:F4)-SUM(G$3:G4)) -> 0.28071588 | P4: =P3+1 -> 2 | Q4: =-1*(SUM(D4)+F4-G4-U4) -> -22404.755 | R4: =(R3+Q4) -> -46581.415 | S4: =SUM(R4)/SUM(C$3:C4) -> -0.25003585 | T4: =T3+(T3*0.03) -> 3605 | U4: =T4*12 -> 43260
A5: =A4+1 -> 3 | B5: =SUM(C$3:C5)/C$1 -> 0.22970526 | C5: =SUMIF(Monthly!A$3:A$362, Yearly!A5, Monthly!D$3:D$362) -> 8950.5276 | D5: =SUMIF(Monthly!A$3:A$362, Yearly!A5, Monthly!E$3:E$362) -> 41557.652 | E5: =SUM(C5:D5) -> 50508.18 | F5: =(9800+11262+2500) -> 23562 | H5: =H4 -> 0.063 | I5: 1198602.7 | J5: =I5-SUM(D$3:D5)-SUM(F$3:F5)-SUM(C6:C$32)+G5 -> 346891.07 | K5: =I5-SUM(D$3:D5)-SUM(F$3:F5)-SUM(C$3:C$32)+SUM(G$3:G5) -> 151641.6 | L5: =K5/(SUM(C$3:D5)+SUM(F$3:F5)-SUM(G$3:G5)) -> 0.38663316 | M5: =I5-SUM(D$3:D5)-SUM(F$3:F5)-SUM(C$3:C$32)+SUM(G$3:G5) -> 151641.6 | N5: =M5/(SUM(C$3:D5)+SUM(F$3:F5)-SUM(G$3:G5)) -> 0.38663316 | P5: =P4+1 -> 3 | Q5: =-1*(SUM(D5)+F5-G5-U5) -> -20561.852 | R5: =(R4+Q5) -> -67143.267 | S5: =SUM(R5)/SUM(C$3:C5) -> -0.3438845 | T5: =T4+(T4*0.03) -> 3713.15 | U5: =T5*12 -> 44557.8
A6: =A5+1 -> 4 | B6: =SUM(C$3:C6)/C$1 -> 0.24091818 | C6: =SUMIF(Monthly!A$3:A$362, Yearly!A6, Monthly!D$3:D$362) -> 9530.9813 | D6: =SUMIF(Monthly!A$3:A$362, Yearly!A6, Monthly!E$3:E$362) -> 40977.198 | E6: =SUM(C6:D6) -> 50508.18 | F6: =(9800+11262+2500) -> 23562 | H6: =H5 -> 0.063 | I6: 1242373 | J6: =I6-SUM(D$3:D6)-SUM(F$3:F6)-SUM(C7:C$32)+G6 -> 335653.2 | K6: =I6-SUM(D$3:D6)-SUM(F$3:F6)-SUM(C$3:C$32)+SUM(G$3:G6) -> 130872.75 | L6: =K6/(SUM(C$3:D6)+SUM(F$3:F6)-SUM(G$3:G6)) -> 0.28067372 | M6: =I6-SUM(D$3:D6)-SUM(F$3:F6)-SUM(C$3:C$32)+SUM(G$3:G6) -> 130872.75 | N6: =M6/(SUM(C$3:D6)+SUM(F$3:F6)-SUM(G$3:G6)) -> 0.28067372 | P6: =P5+1 -> 4 | Q6: =-1*(SUM(D6)+F6-G6-U6) -> -18644.664 | R6: =(R5+Q6) -> -85787.932 | S6: =SUM(R6)/SUM(C$3:C6) -> -0.41892637 | T6: =T5+(T5*0.03) -> 3824.5445 | U6: =T6*12 -> 45894.534
A7: =A6+1 -> 5 | B7: =SUM(C$3:C7)/C$1 -> 0.25285827 | C7: =SUMIF(Monthly!A$3:A$362, Yearly!A7, Monthly!D$3:D$362) -> 10149.078 | D7: =SUMIF(Monthly!A$3:A$362, Yearly!A7, Monthly!E$3:E$362) -> 40359.101 | E7: =SUM(C7:D7) -> 50508.18 | F7: =(9800+11262+2500) -> 23562 | H7: =H6 -> 0.063 | I7: 1258973.6 | J7: =I7-SUM(D$3:D7)-SUM(F$3:F7)-SUM(C8:C$32)+G7 -> 298481.8 | K7: =I7-SUM(D$3:D7)-SUM(F$3:F7)-SUM(C$3:C$32)+SUM(G$3:G7) -> 83552.268 | L7: =K7/(SUM(C$3:D7)+SUM(F$3:F7)-SUM(G$3:G7)) -> 0.15462595 | M7: =I7-SUM(D$3:D7)-SUM(F$3:F7)-SUM(C$3:C$32)+SUM(G$3:G7) -> 83552.268 | N7: =M7/(SUM(C$3:D7)+SUM(F$3:F7)-SUM(G$3:G7)) -> 0.15462595 | P7: =P6+1 -> 5 | Q7: =-1*(SUM(D7)+F7-G7-U7) -> -16649.731 | R7: =(R6+Q7) -> -102437.66 | S7: =SUM(R7)/SUM(C$3:C7) -> -0.47661046 | T7: =T6+(T6*0.03) -> 3939.2808 | U7: =T7*12 -> 47271.37
A8: =A7+1 -> 6 | B8: =SUM(C$3:C8)/C$1 -> 0.26557269 | C8: =SUMIF(Monthly!A$3:A$362, Yearly!A8, Monthly!D$3:D$362) -> 10807.26 | D8: =SUMIF(Monthly!A$3:A$362, Yearly!A8, Monthly!E$3:E$362) -> 39700.92 | E8: =SUM(C8:D8) -> 50508.18 | F8: =(9800+11262+2500) -> 23562 | H8: =H7 -> 0.063 | I8: 1487175.1 | J8: =I8-SUM(D$3:D8)-SUM(F$3:F8)-SUM(C9:C$32)+G8 -> 474227.63 | K8: =I8-SUM(D$3:D8)-SUM(F$3:F8)-SUM(C$3:C$32)+SUM(G$3:G8) -> 248490.84 | L8: =K8/(SUM(C$3:D8)+SUM(F$3:F8)-SUM(G$3:G8)) -> 0.40443085 | M8: =I7-SUM(D$3:D7)-SUM(F$3:F7)-SUM(C$3:C$32)+SUM(G$3:G7)+SUM(U$8:U8) -> 132241.78 | N8: =M8/(SUM(C$3:D8)+SUM(F$3:F8)-SUM(G$3:G8)) -> 0.21522989 | P8: =P7+1 -> 6 | Q8: =-1*(SUM(D8)+F8-G8-U8) -> -14573.409 | R8: =(R7+Q8) -> -117011.07 | S8: =SUM(R8)/SUM(C$3:C8) -> -0.5183518 | T8: =T7+(T7*0.03) -> 4057.4593 | U8: =T8*12 -> 48689.511
A9: =A8+1 -> 7 | B9: =SUM(C$3:C9)/C$1 -> 0.27911167 | C9: =SUMIF(Monthly!A$3:A$362, Yearly!A9, Monthly!D$3:D$362) -> 11508.125 | D9: =SUMIF(Monthly!A$3:A$362, Yearly!A9, Monthly!E$3:E$362) -> 39000.055 | E9: =SUM(C9:D9) -> 50508.18 | F9: =(9800+11262+2500) -> 23562 | H9: =H8 -> 0.063 | I9: 1573996.5 | J9: =I9-SUM(D$3:D9)-SUM(F$3:F9)-SUM(C10:C$32)+G9 -> 509995.05 | K9: =I9-SUM(D$3:D9)-SUM(F$3:F9)-SUM(C$3:C$32)+SUM(G$3:G9) -> 272750.13 | L9: =K9/(SUM(C$3:D9)+SUM(F$3:F9)-SUM(G$3:G9)) -> 0.39615627 | M9: =I8-SUM(D$3:D8)-SUM(F$3:F8)-SUM(C$3:C$32)+SUM(G$3:G8)+SUM(U$8:U9) -> 347330.55 | N9: =M9/(SUM(C$3:D9)+SUM(F$3:F9)-SUM(G$3:G9)) -> 0.5044807 | P9: =P8+1 -> 7 | Q9: =-1*(SUM(D9)+F9-G9-U9) -> -12411.858 | R9: =(R8+Q9) -> -129422.93 | S9: =SUM(R9)/SUM(C$3:C9) -> -0.54552457 | T9: =T8+(T8*0.03) -> 4179.183 | U9: =T9*12 -> 50150.196
A10: =A9+1 -> 8 | B10: =SUM(C$3:C10)/C$1 -> 0.29352866 | C10: =SUMIF(Monthly!A$3:A$362, Yearly!A10, Monthly!D$3:D$362) -> 12254.442 | D10: =SUMIF(Monthly!A$3:A$362, Yearly!A10, Monthly!E$3:E$362) -> 38253.738 | E10: =SUM(C10:D10) -> 50508.18 | F10: =(9800+11262+2500) -> 23562 | H10: =H9 -> 0.063 | I10: 1596553.8 | J10: =I10-SUM(D$3:D10)-SUM(F$3:F10)-SUM(C11:C$32)+G10 -> 482991.04 | K10: =I10-SUM(D$3:D10)-SUM(F$3:F10)-SUM(C$3:C$32)+SUM(G$3:G10) -> 233491.68 | L10: =K10/(SUM(C$3:D10)+SUM(F$3:F10)-SUM(G$3:G10)) -> 0.30619392 | M10: =I10-SUM(D$3:D10)-SUM(F$3:F10)-SUM(C$3:C$32)+SUM(G$3:G10)+SUM(U$8:U10) -> 383986.09 | N10: =M10/(SUM(C$3:D10)+SUM(F$3:F10)-SUM(G$3:G10)) -> 0.50354774 | P10: =P9+1 -> 8 | Q10: =-1*(SUM(D10)+F10-G10-U10) -> -10161.035 | R10: =(R9+Q10) -> -139583.97 | S10: =SUM(R10)/SUM(C$3:C10) -> -0.55945621 | T10: =T9+(T9*0.03) -> 4304.5585 | U10: =T10*12 -> 51654.702
A11: =A10+1 -> 9 | B11: =SUM(C$3:C11)/C$1 -> 0.30888061 | C11: =SUMIF(Monthly!A$3:A$362, Yearly!A11, Monthly!D$3:D$362) -> 13049.159 | D11: =SUMIF(Monthly!A$3:A$362, Yearly!A11, Monthly!E$3:E$362) -> 37459.021 | E11: =SUM(C11:D11) -> 50508.18 | F11: =(9800+11262+2500) -> 23562 | H11: =H10 -> 0.063 | I11: 1535180.4 | J11: =I11-SUM(D$3:D11)-SUM(F$3:F11)-SUM(C12:C$32)+G11 -> 373645.8 | K11: =I11-SUM(D$3:D11)-SUM(F$3:F11)-SUM(C$3:C$32)+SUM(G$3:G11) -> 111097.29 | L11: =K11/(SUM(C$3:D11)+SUM(F$3:F11)-SUM(G$3:G11)) -> 0.13279116 | M11: =I11-SUM(D$3:D11)-SUM(F$3:F11)-SUM(C$3:C$32)+SUM(G$3:G11)+SUM(U$8:U11) -> 314796.04 | N11: =M11/(SUM(C$3:D11)+SUM(F$3:F11)-SUM(G$3:G11)) -> 0.37626601 | P11: =P10+1 -> 9 | Q11: =-1*(SUM(D11)+F11-G11-U11) -> -7816.6771 | R11: =(R10+Q11) -> -147400.64 | S11: =SUM(R11)/SUM(C$3:C11) -> -0.56142249 | T11: =T10+(T10*0.03) -> 4433.6953 | U11: =T11*12 -> 53204.343
A12: =A11+1 -> 10 | B12: =SUM(C$3:C12)/C$1 -> 0.32522815 | C12: =SUMIF(Monthly!A$3:A$362, Yearly!A12, Monthly!D$3:D$362) -> 13895.415 | D12: =SUMIF(Monthly!A$3:A$362, Yearly!A12, Monthly!E$3:E$362) -> 36612.765 | E12: =SUM(C12:D12) -> 50508.18 | F12: =(9800+11262+2500) -> 23562 | H12: =H11 -> 0.063 | I12: 1537243.5 | J12: =I12-SUM(D$3:D12)-SUM(F$3:F12)-SUM(C13:C$32)+G12 -> 329429.6 | K12: =I12-SUM(D$3:D12)-SUM(F$3:F12)-SUM(C$3:C$32)+SUM(G$3:G12) -> 52985.672 | L12: =K12/(SUM(C$3:D12)+SUM(F$3:F12)-SUM(G$3:G12)) -> 0.058181144 | M12: =I12-SUM(D$3:D12)-SUM(F$3:F12)-SUM(C$3:C$32)+SUM(G$3:G12)+SUM(U$8:U12) -> 311484.9 | N12: =M12/(SUM(C$3:D12)+SUM(F$3:F12)-SUM(G$3:G12)) -> 0.34202732 | P12: =P11+1 -> 10 | Q12: =-1*(SUM(D12)+F12-G12-U12) -> -5374.2914 | R12: =(R11+Q12) -> -152774.93 | S12: =SUM(R12)/SUM(C$3:C12) -> -0.55264347 | T12: =T11+(T11*0.03) -> 4566.7061 | U12: =T12*12 -> 54800.474
A13: =A12+1 -> 11 | B13: =SUM(C$3:C13)/C$1 -> 0.34263586 | C13: =SUMIF(Monthly!A$3:A$362, Yearly!A13, Monthly!D$3:D$362) -> 14796.551 | D13: =SUMIF(Monthly!A$3:A$362, Yearly!A13, Monthly!E$3:E$362) -> 35711.629 | E13: =SUM(C13:D13) -> 50508.18 | F13: =(9800+11262+2500) -> 23562 | H13: =H12 -> 0.063 | I13: 1551294.3 | J13: =I13-SUM(D$3:D13)-SUM(F$3:F13)-SUM(C14:C$32)+G13 -> 299003.32 | K13: =I13-SUM(D$3:D13)-SUM(F$3:F13)-SUM(C$3:C$32)+SUM(G$3:G13) -> 7762.836 | L13: =K13/(SUM(C$3:D13)+SUM(F$3:F13)-SUM(G$3:G13)) -> 0.0078828767 | M13: =I13-SUM(D$3:D13)-SUM(F$3:F13)-SUM(C$3:C$32)+SUM(G$3:G13)+SUM(U$8:U13) -> 322706.55 | N13: =M13/(SUM(C$3:D13)+SUM(F$3:F13)-SUM(G$3:G13)) -> 0.32769672 | P13: =P12+1 -> 11 | Q13: =-1*(SUM(D13)+F13-G13-U13) -> -2829.1409 | R13: =(R12+Q13) -> -155604.08 | S13: =SUM(R13)/SUM(C$3:C13) -> -0.53428038 | T13: =T12+(T12*0.03) -> 4703.7073 | U13: =T13*12 -> 56444.488
A14: =A13+1 -> 12 | B14: =SUM(C$3:C14)/C$1 -> 0.36117248 | C14: =SUMIF(Monthly!A$3:A$362, Yearly!A14, Monthly!D$3:D$362) -> 15756.127 | D14: =SUMIF(Monthly!A$3:A$362, Yearly!A14, Monthly!E$3:E$362) -> 34752.053 | E14: =SUM(C14:D14) -> 50508.18 | F14: =(9800+11262+2500) -> 23562 | H14: =H13 -> 0.063 | I14: 1634838.6 | J14: =I14-SUM(D$3:D14)-SUM(F$3:F14)-SUM(C15:C$32)+G14 -> 339989.71 | K14: =I14-SUM(D$3:D14)-SUM(F$3:F14)-SUM(C$3:C$32)+SUM(G$3:G14) -> 32993.099 | L14: =K14/(SUM(C$3:D14)+SUM(F$3:F14)-SUM(G$3:G14)) -> 0.031159601 | M14: =I14-SUM(D$3:D14)-SUM(F$3:F14)-SUM(C$3:C$32)+SUM(G$3:G14)+SUM(U$8:U14) -> 406074.64 | N14: =M14/(SUM(C$3:D14)+SUM(F$3:F14)-SUM(G$3:G14)) -> 0.38350819 | P14: =P13+1 -> 12 | Q14: =-1*(SUM(D14)+F14-G14-U14) -> -176.23018 | R14: =(R13+Q14) -> -155780.31 | S14: =SUM(R14)/SUM(C$3:C14) -> -0.50743331 | T14: =T13+(T13*0.03) -> 4844.8185 | U14: =T14*12 -> 58137.823
A15: =A14+1 -> 13 | B15: =SUM(C$3:C15)/C$1 -> 0.38091123 | C15: =SUMIF(Monthly!A$3:A$362, Yearly!A15, Monthly!D$3:D$362) -> 16777.933 | D15: =SUMIF(Monthly!A$3:A$362, Yearly!A15, Monthly!E$3:E$362) -> 33730.247 | E15: =SUM(C15:D15) -> 50508.18 | F15: =(9800+11262+2500) -> 23562 | H15: =H14 -> 0.063 | I15: 1723020.8 | J15: =I15-SUM(D$3:D15)-SUM(F$3:F15)-SUM(C16:C$32)+G15 -> 387657.52 | K15: =I15-SUM(D$3:D15)-SUM(F$3:F15)-SUM(C$3:C$32)+SUM(G$3:G15) -> 63882.98 | L15: =K15/(SUM(C$3:D15)+SUM(F$3:F15)-SUM(G$3:G15)) -> 0.056388282 | M15: =I15-SUM(D$3:D15)-SUM(F$3:F15)-SUM(C$3:C$32)+SUM(G$3:G15)+SUM(U$8:U15) -> 496846.47 | N15: =M15/(SUM(C$3:D15)+SUM(F$3:F15)-SUM(G$3:G15)) -> 0.43855686 | P15: =P14+1 -> 13 | Q15: =-1*(SUM(D15)+F15-G15-U15) -> 2589.7104 | R15: =(R14+Q15) -> -153190.59 | S15: =SUM(R15)/SUM(C$3:C15) -> -0.47313972 | T15: =T14+(T14*0.03) -> 4990.1631 | U15: =T15*12 -> 59881.957
A16: =A15+1 -> 14 | B16: =SUM(C$3:C16)/C$1 -> 0.40193005 | C16: =SUMIF(Monthly!A$3:A$362, Yearly!A16, Monthly!D$3:D$362) -> 17866.004 | D16: =SUMIF(Monthly!A$3:A$362, Yearly!A16, Monthly!E$3:E$362) -> 32642.175 | E16: =SUM(C16:D16) -> 50508.18 | F16: =(9800+11262+2500) -> 23562 | H16: =H15 -> 0.063 | I16: 1971577.8 | J16: =I16-SUM(D$3:D16)-SUM(F$3:F16)-SUM(C17:C$32)+G16 -> 597876.39 | K16: =I16-SUM(D$3:D16)-SUM(F$3:F16)-SUM(C$3:C$32)+SUM(G$3:G16) -> 256235.85 | L16: =K16/(SUM(C$3:D16)+SUM(F$3:F16)-SUM(G$3:G16)) -> 0.21229458 | M16: =I16-SUM(D$3:D16)-SUM(F$3:F16)-SUM(C$3:C$32)+SUM(G$3:G16)+SUM(U$8:U16) -> 750877.76 | N16: =M16/(SUM(C$3:D16)+SUM(F$3:F16)-SUM(G$3:G16)) -> 0.62211155 | P16: =P15+1 -> 14 | Q16: =-1*(SUM(D16)+F16-G16-U16) -> 5474.2405 | R16: =(R15+Q16) -> -147716.35 | S16: =SUM(R16)/SUM(C$3:C16) -> -0.4323736 | T16: =T15+(T15*0.03) -> 5139.868 | U16: =T16*12 -> 61678.416
A17: =A16+1 -> 15 | B17: =SUM(C$3:C17)/C$1 -> 0.42431198 | C17: =SUMIF(Monthly!A$3:A$362, Yearly!A17, Monthly!D$3:D$362) -> 19024.638 | D17: =SUMIF(Monthly!A$3:A$362, Yearly!A17, Monthly!E$3:E$362) -> 31483.541 | E17: =SUM(C17:D17) -> 50508.18 | F17: =(9800+11262+2500) -> 23562 | H17: =H16 -> 0.063 | I17: 2191844.5 | J17: =I17-SUM(D$3:D17)-SUM(F$3:F17)-SUM(C18:C$32)+G17 -> 782122.2 | K17: =I17-SUM(D$3:D17)-SUM(F$3:F17)-SUM(C$3:C$32)+SUM(G$3:G17) -> 421457.01 | L17: =K17/(SUM(C$3:D17)+SUM(F$3:F17)-SUM(G$3:G17)) -> 0.32899272 | M17: =I17-SUM(D$3:D17)-SUM(F$3:F17)-SUM(C$3:C$32)+SUM(G$3:G17)+SUM(U$8:U17) -> 979627.69 | N17: =M17/(SUM(C$3:D17)+SUM(F$3:F17)-SUM(G$3:G17)) -> 0.76470523 | P17: =P16+1 -> 15 | Q17: =-1*(SUM(D17)+F17-G17-U17) -> 8483.2273 | R17: =(R16+Q17) -> -139233.13 | S17: =SUM(R17)/SUM(C$3:C17) -> -0.38604538 | T17: =T16+(T16*0.03) -> 5294.064 | U17: =T17*12 -> 63528.768
A18: =A17+1 -> 16 | B18: =SUM(C$3:C18)/C$1 -> 0.44814541 | C18: =SUMIF(Monthly!A$3:A$362, Yearly!A18, Monthly!D$3:D$362) -> 20258.412 | D18: =SUMIF(Monthly!A$3:A$362, Yearly!A18, Monthly!E$3:E$362) -> 30249.768 | E18: =SUM(C18:D18) -> 50508.18 | F18: =(9800+11262+2500) -> 23562 | H18: =H17 -> 0.063 | I18: 2293214.7 | J18: =I18-SUM(D$3:D18)-SUM(F$3:F18)-SUM(C19:C$32)+G18 -> 849939.07 | K18: =I18-SUM(D$3:D18)-SUM(F$3:F18)-SUM(C$3:C$32)+SUM(G$3:G18) -> 469015.47 | L18: =K18/(SUM(C$3:D18)+SUM(F$3:F18)-SUM(G$3:G18)) -> 0.34610549 | M18: =I18-SUM(D$3:D18)-SUM(F$3:F18)-SUM(C$3:C$32)+SUM(G$3:G18)+SUM(U$8:U18) -> 1092620.8 | N18: =M18/(SUM(C$3:D18)+SUM(F$3:F18)-SUM(G$3:G18)) -> 0.80628908 | P18: =P17+1 -> 16 | Q18: =-1*(SUM(D18)+F18-G18-U18) -> 11622.864 | R18: =(R17+Q18) -> -127610.26 | S18: =SUM(R18)/SUM(C$3:C18) -> -0.33500225 | T18: =T17+(T17*0.03) -> 5452.886 | U18: =T18*12 -> 65434.631
A19: =A18+1 -> 17 | B19: =SUM(C$3:C19)/C$1 -> 0.47352446 | C19: =SUMIF(Monthly!A$3:A$362, Yearly!A19, Monthly!D$3:D$362) -> 21572.197 | D19: =SUMIF(Monthly!A$3:A$362, Yearly!A19, Monthly!E$3:E$362) -> 28935.983 | E19: =SUM(C19:D19) -> 50508.18 | F19: =(9800+11262+2500) -> 23562 | H19: =H18 -> 0.063 | I19: 2427154.7 | J19: =I19-SUM(D$3:D19)-SUM(F$3:F19)-SUM(C20:C$32)+G19 -> 952953.19 | K19: =I19-SUM(D$3:D19)-SUM(F$3:F19)-SUM(C$3:C$32)+SUM(G$3:G19) -> 550457.39 | L19: =K19/(SUM(C$3:D19)+SUM(F$3:F19)-SUM(G$3:G19)) -> 0.38515258 | M19: =I19-SUM(D$3:D19)-SUM(F$3:F19)-SUM(C$3:C$32)+SUM(G$3:G19)+SUM(U$8:U19) -> 1241460.4 | N19: =M19/(SUM(C$3:D19)+SUM(F$3:F19)-SUM(G$3:G19)) -> 0.86864428 | P19: =P18+1 -> 17 | Q19: =-1*(SUM(D19)+F19-G19-U19) -> 14899.688 | R19: =(R18+Q19) -> -112710.58 | S19: =SUM(R19)/SUM(C$3:C19) -> -0.2800292 | T19: =T18+(T18*0.03) -> 5616.4725 | U19: =T19*12 -> 67397.67
A20: =A19+1 -> 18 | B20: =SUM(C$3:C20)/C$1 -> 0.50054938 | C20: =SUMIF(Monthly!A$3:A$362, Yearly!A20, Monthly!D$3:D$362) -> 22971.183 | D20: =SUMIF(Monthly!A$3:A$362, Yearly!A20, Monthly!E$3:E$362) -> 27536.997 | E20: =SUM(C20:D20) -> 50508.18 | F20: =(9800+11262+2500) -> 23562 | H20: =H19 -> 0.063 | I20: 2485577 | J20: =I20-SUM(D$3:D20)-SUM(F$3:F20)-SUM(C21:C$32)+G20 -> 983247.75 | K20: =I20-SUM(D$3:D20)-SUM(F$3:F20)-SUM(C$3:C$32)+SUM(G$3:G20) -> 557780.78 | L20: =K20/(SUM(C$3:D20)+SUM(F$3:F20)-SUM(G$3:G20)) -> 0.37104664 | M20: =I20-SUM(D$3:D20)-SUM(F$3:F20)-SUM(C$3:C$32)+SUM(G$3:G20)+SUM(U$8:U20) -> 1318203.4 | N20: =M20/(SUM(C$3:D20)+SUM(F$3:F20)-SUM(G$3:G20)) -> 0.87689457 | P20: =P19+1 -> 18 | Q20: =-1*(SUM(D20)+F20-G20-U20) -> 18320.604 | R20: =(R19+Q20) -> -94389.972 | S20: =SUM(R20)/SUM(C$3:C20) -> -0.22185029 | T20: =T19+(T19*0.03) -> 5784.9667 | U20: =T20*12 -> 69419.601
A21: =A20+1 -> 19 | B21: =SUM(C$3:C21)/C$1 -> 0.52932691 | C21: =SUMIF(Monthly!A$3:A$362, Yearly!A21, Monthly!D$3:D$362) -> 24460.895 | D21: =SUMIF(Monthly!A$3:A$362, Yearly!A21, Monthly!E$3:E$362) -> 26047.285 | E21: =SUM(C21:D21) -> 50508.18 | F21: =(9800+11262+2500) -> 23562 | H21: =H20 -> 0.063 | I21: 2501454.9 | J21: =I21-SUM(D$3:D21)-SUM(F$3:F21)-SUM(C22:C$32)+G21 -> 973977.22 | K21: =I21-SUM(D$3:D21)-SUM(F$3:F21)-SUM(C$3:C$32)+SUM(G$3:G21) -> 524049.35 | L21: =K21/(SUM(C$3:D21)+SUM(F$3:F21)-SUM(G$3:G21)) -> 0.33223753 | M21: =I21-SUM(D$3:D21)-SUM(F$3:F21)-SUM(C$3:C$32)+SUM(G$3:G21)+SUM(U$8:U21) -> 1355974.1 | N21: =M21/(SUM(C$3:D21)+SUM(F$3:F21)-SUM(G$3:G21)) -> 0.85966233 | P21: =P20+1 -> 19 | Q21: =-1*(SUM(D21)+F21-G21-U21) -> 21892.904 | R21: =(R20+Q21) -> -72497.068 | S21: =SUM(R21)/SUM(C$3:C21) -> -0.16113042 | T21: =T20+(T20*0.03) -> 5958.5157 | U21: =T21*12 -> 71502.189
... A31: =A30+1 -> 29 | B31: =SUM(C$3:C31)/C$1 -> 0.94255765 | C31: =SUMIF(Monthly!A$3:A$362, Yearly!A31, Monthly!D$3:D$362) -> 45852.408 | D31: =SUMIF(Monthly!A$3:A$362, Yearly!A31, Monthly!E$3:E$362) -> 4655.7713 | E31: =SUM(C31:D31) -> 50508.18 | F31: =(9800+11262+2500) -> 23562 | H31: =H30 -> 0.063 | I31: 3329071 | J31: =I31-SUM(D$3:D31)-SUM(F$3:F31)-SUM(C32:C$32)+G31 -> 1763383.8 | K31: =I31-SUM(D$3:D31)-SUM(F$3:F31)-SUM(C$3:C$32)+SUM(G$3:G31) -> 962209.82 | L31: =K31/(SUM(C$3:D31)+SUM(F$3:F31)-SUM(G$3:G31)) -> 0.41509715 | M31: =I31-SUM(D$3:D31)-SUM(F$3:F31)-SUM(C$3:C$32)+SUM(G$3:G31)+SUM(U$8:U31) -> 2638417.8 | N31: =M31/(SUM(C$3:D31)+SUM(F$3:F31)-SUM(G$3:G31)) -> 1.138213 | P31: =P30+1 -> 29 | Q31: =-1*(SUM(D31)+F31-G31-U31) -> 67875.191 | R31: =(R30+Q31) -> 382330.5 | S31: =SUM(R31)/SUM(C$3:C31) -> 0.47721282 | T31: =T30+(T30*0.03) -> 8007.7469 | U31: =T31*12 -> 96092.962
A32: =A31+1 -> 30 | B32: =SUM(C$3:C32)/C$1 -> 1 | C32: =SUMIF(Monthly!A$3:A$362, Yearly!A32, Monthly!D$3:D$362) -> 48825.998 | D32: =SUMIF(Monthly!A$3:A$362, Yearly!A32, Monthly!E$3:E$362) -> 1682.1812 | E32: =SUM(C32:D32) -> 50508.18 | F32: =(9800+11262+2500) -> 23562 | H32: =H31 -> 0.063 | I32: 3444545.2 | J32: =I32-SUM(D$3:D32)-SUM(F$3:F32)-SUM(C$32:C33)+G32 -> 1853613.8 | K32: =I32-SUM(D$3:D32)-SUM(F$3:F32)-SUM(C$3:C$32)+SUM(G$3:G32) -> 1052439.8 | L32: =K32/(SUM(C$3:D32)+SUM(F$3:F32)-SUM(G$3:G32)) -> 0.43996383 | M32: =I32-SUM(D$3:D32)-SUM(F$3:F32)-SUM(C$3:C$32)+SUM(G$3:G32)+SUM(U$8:U32) -> 2827623.6 | N32: =M32/(SUM(C$3:D32)+SUM(F$3:F32)-SUM(G$3:G32)) -> 1.1820648 | P32: =P31+1 -> 30 | Q32: =-1*(SUM(D32)+F32-G32-U32) -> 73731.57 | R32: =(R31+Q32) -> 456062.07 | S32: =SUM(R32)/SUM(C$3:C32) -> 0.53654361 | T32: =T31+(T31*0.03) -> 8247.9793 | U32: =T32*12 -> 98975.751

Sheet Monthly
C1: Home Price: | D1: 850000 | E1: Down Payment: | F1: 0.2 | G1: Total Monthly Cost: | H1: =((SUM(F3:G3))) -> 6172.515
A2: Year | B2: Month | C2: % Equity in Home | D2: Principal | E2: Interest | F2: Total Monthly Payment | G2: Taxes, HOA Fees, Insurance, Etc | H2: Tax Savings | I2: Interest Rate
A3: =ROUNDUP(B3/12,0) -> 1 | B3: 1 | C3: =SUM(D$3:D3)/D$1 -> 0.20075178 | D3: =(F$1*D1)+F3-E3 -> 170639.01 | E3: =(((1-F$1)*D$1)*(I3/12)) -> 3570 | F3: =((1-F$1)*D$1)*(((I3/12)*((1+(I3/12))^(12*30)))/(((1+(I3/12))^(12*30))-1)) -> 4209.015 | G3: =(9800+11262+2500)/12 -> 1963.5 | I3: 0.063
A4: =ROUNDUP(B4/12,0) -> 1 | B4: =B3+1 -> 2 | C4: =SUM(D$3:D4)/D$1 -> 0.20150751 | D4: =F4-E4 -> 642.3698 | E4: =((((1-F$1)*D$1)-SUM(D$3:D3)+((F$1)*D$1))*(I4/12)) -> 3566.6452 | F4: =((1-F$1)*D$1)*(((I4/12)*((1+(I4/12))^(12*30)))/(((1+(I4/12))^(12*30))-1)) -> 4209.015 | G4: =(9800+11262+2500)/12 -> 1963.5 | I4: 0.063
A5: =ROUNDUP(B5/12,0) -> 1 | B5: =B4+1 -> 3 | C5: =SUM(D$3:D5)/D$1 -> 0.20226721 | D5: =F5-E5 -> 645.74224 | E5: =((((1-F$1)*D$1)-SUM(D$3:D4)+((F$1)*D$1))*(I5/12)) -> 3563.2727 | F5: =((1-F$1)*D$1)*(((I5/12)*((1+(I5/12))^(12*30)))/(((1+(I5/12))^(12*30))-1)) -> 4209.015 | G5: =(9800+11262+2500)/12 -> 1963.5 | I5: 0.063
A6: =ROUNDUP(B6/12,0) -> 1 | B6: =B5+1 -> 4 | C6: =SUM(D$3:D6)/D$1 -> 0.20303089 | D6: =F6-E6 -> 649.13239 | E6: =((((1-F$1)*D$1)-SUM(D$3:D5)+((F$1)*D$1))*(I6/12)) -> 3559.8826 | F6: =((1-F$1)*D$1)*(((I6/12)*((1+(I6/12))^(12*30)))/(((1+(I6/12))^(12*30))-1)) -> 4209.015 | G6: =(9800+11262+2500)/12 -> 1963.5 | I6: 0.063
A7: =ROUNDUP(B7/12,0) -> 1 | B7: =B6+1 -> 5 | C7: =SUM(D$3:D7)/D$1 -> 0.20379859 | D7: =F7-E7 -> 652.54033 | E7: =((((1-F$1)*D$1)-SUM(D$3:D6)+((F$1)*D$1))*(I7/12)) -> 3556.4746 | F7: =((1-F$1)*D$1)*(((I7/12)*((1+(I7/12))^(12*30)))/(((1+(I7/12))^(12*30))-1)) -> 4209.015 | G7: =(9800+11262+2500)/12 -> 1963.5 | I7: 0.063
A8: =ROUNDUP(B8/12,0) -> 1 | B8: =B7+1 -> 6 | C8: =SUM(D$3:D8)/D$1 -> 0.20457031 | D8: =F8-E8 -> 655.96617 | E8: =((((1-F$1)*D$1)-SUM(D$3:D7)+((F$1)*D$1))*(I8/12)) -> 3553.0488 | F8: =((1-F$1)*D$1)*(((I8/12)*((1+(I8/12))^(12*30)))/(((1+(I8/12))^(12*30))-1)) -> 4209.015 | G8: =(9800+11262+2500)/12 -> 1963.5 | I8: 0.063
A9: =ROUNDUP(B9/12,0) -> 1 | B9: =B8+1 -> 7 | C9: =SUM(D$3:D9)/D$1 -> 0.20534609 | D9: =F9-E9 -> 659.40999 | E9: =((((1-F$1)*D$1)-SUM(D$3:D8)+((F$1)*D$1))*(I9/12)) -> 3549.605 | F9: =((1-F$1)*D$1)*(((I9/12)*((1+(I9/12))^(12*30)))/(((1+(I9/12))^(12*30))-1)) -> 4209.015 | G9: =(9800+11262+2500)/12 -> 1963.5 | I9: 0.063
A10: =ROUNDUP(B10/12,0) -> 1 | B10: =B9+1 -> 8 | C10: =SUM(D$3:D10)/D$1 -> 0.20612594 | D10: =F10-E10 -> 662.87189 | E10: =((((1-F$1)*D$1)-SUM(D$3:D9)+((F$1)*D$1))*(I10/12)) -> 3546.1431 | F10: =((1-F$1)*D$1)*(((I10/12)*((1+(I10/12))^(12*30)))/(((1+(I10/12))^(12*30))-1)) -> 4209.015 | G10: =(9800+11262+2500)/12 -> 1963.5 | I10: 0.063
A11: =ROUNDUP(B11/12,0) -> 1 | B11: =B10+1 -> 9 | C11: =SUM(D$3:D11)/D$1 -> 0.20690988 | D11: =F11-E11 -> 666.35197 | E11: =((((1-F$1)*D$1)-SUM(D$3:D10)+((F$1)*D$1))*(I11/12)) -> 3542.663 | F11: =((1-F$1)*D$1)*(((I11/12)*((1+(I11/12))^(12*30)))/(((1+(I11/12))^(12*30))-1)) -> 4209.015 | G11: =(9800+11262+2500)/12 -> 1963.5 | I11: 0.063
A12: =ROUNDUP(B12/12,0) -> 1 | B12: =B11+1 -> 10 | C12: =SUM(D$3:D12)/D$1 -> 0.20769794 | D12: =F12-E12 -> 669.85032 | E12: =((((1-F$1)*D$1)-SUM(D$3:D11)+((F$1)*D$1))*(I12/12)) -> 3539.1647 | F12: =((1-F$1)*D$1)*(((I12/12)*((1+(I12/12))^(12*30)))/(((1+(I12/12))^(12*30))-1)) -> 4209.015 | G12: =(9800+11262+2500)/12 -> 1963.5 | I12: 0.063
A13: =ROUNDUP(B13/12,0) -> 1 | B13: =B12+1 -> 11 | C13: =SUM(D$3:D13)/D$1 -> 0.20849014 | D13: =F13-E13 -> 673.36703 | E13: =((((1-F$1)*D$1)-SUM(D$3:D12)+((F$1)*D$1))*(I13/12)) -> 3535.6479 | F13: =((1-F$1)*D$1)*(((I13/12)*((1+(I13/12))^(12*30)))/(((1+(I13/12))^(12*30))-1)) -> 4209.015 | G13: =(9800+11262+2500)/12 -> 1963.5 | I13: 0.063
A14: =ROUNDUP(B14/12,0) -> 1 | B14: =B13+1 -> 12 | C14: =SUM(D$3:D14)/D$1 -> 0.20928649 | D14: =F14-E14 -> 676.90221 | E14: =((((1-F$1)*D$1)-SUM(D$3:D13)+((F$1)*D$1))*(I14/12)) -> 3532.1128 | F14: =((1-F$1)*D$1)*(((I14/12)*((1+(I14/12))^(12*30)))/(((1+(I14/12))^(12*30))-1)) -> 4209.015 | G14: =(9800+11262+2500)/12 -> 1963.5 | I14: 0.063
A15: =ROUNDUP(B15/12,0) -> 2 | B15: =B14+1 -> 13 | C15: =SUM(D$3:D15)/D$1 -> 0.21008703 | D15: =F15-E15 -> 680.45594 | E15: =((((1-F$1)*D$1)-SUM(D$3:D14)+((F$1)*D$1))*(I15/12)) -> 3528.559 | F15: =((1-F$1)*D$1)*(((I15/12)*((1+(I15/12))^(12*30)))/(((1+(I15/12))^(12*30))-1)) -> 4209.015 | G15: =(9800+11262+2500)/12 -> 1963.5 | I15: 0.063
... A362: =ROUNDUP(B362/12,0) -> 30 | B362: =B361+1 -> 360 | C362: =SUM(D$3:D362)/D$1 -> 1 | D362: =F362-E362 -> 4187.033 | E362: =((((1-F$1)*D$1)-SUM(D$3:D361)+((F$1)*D$1))*(I362/12)) -> 21.981923 | F362: =((1-F$1)*D$1)*(((I362/12)*((1+(I362/12))^(12*30)))/(((1+(I362/12))^(12*30))-1)) -> 4209.015 | G362: =(9800+11262+2500)/12 -> 1963.5 | I362: 0.063
